ccob/__init__.py
ccob/ccob.py
ccob/cli.py
ccob-0.1.1.dist-info/METADATA
ccob-0.1.1.dist-info/WHEEL
ccob-0.1.1.dist-info/entry_points.txt
ccob-0.1.1.dist-info/licenses/AUTHORS.rst
ccob-0.1.1.dist-info/licenses/LICENSE
ccob-0.1.1.dist-info/RECORD
