Metadata-Version: 2.4
Name: ccob
Version: 0.1.1
Summary: Cookiecutter Template for Obsidian.
Project-URL: Repository, https://gitee.com/gooker_young/ccob
Project-URL: Documentation, https://ccob.readthedocs.io/zh-cn/stable/
Project-URL: Issues, https://gitee.com/gooker_young/ccob/issues
Author-email: gooker_young <gooker_young@qq.com>
Maintainer-email: gooker_young <gooker_young@qq.com>
License: MIT license
License-File: AUTHORS.rst
License-File: LICENSE
Requires-Python: >=3.8
Requires-Dist: rich>=13.9.4
Requires-Dist: typer>=0.15.1
